README.md
setup.py
data_integration/__init__.py
data_integration/config.py
data_integration/events.py
data_integration/execution.py
data_integration/pipelines.py
data_integration/shell.py
data_integration.egg-info/PKG-INFO
data_integration.egg-info/SOURCES.txt
data_integration.egg-info/dependency_links.txt
data_integration.egg-info/requires.txt
data_integration.egg-info/top_level.txt
data_integration/commands/__init__.py
data_integration/commands/bash.py
data_integration/commands/files.py
data_integration/commands/python.py
data_integration/commands/sql.py
data_integration/incremental_processing/__init__.py
data_integration/incremental_processing/file_dependencies.py
data_integration/incremental_processing/incremental_copy_status.py
data_integration/incremental_processing/processed_files.py
data_integration/incremental_processing/reset.py
data_integration/logging/__init__.py
data_integration/logging/logger.py
data_integration/logging/node_cost.py
data_integration/logging/pipeline_events.py
data_integration/logging/run_log.py
data_integration/logging/system_statistics.py
data_integration/notification/__init__.py
data_integration/notification/notifier.py
data_integration/notification/slack.py
data_integration/notification/teams.py
data_integration/parallel_tasks/__init__.py
data_integration/parallel_tasks/files.py
data_integration/parallel_tasks/python.py
data_integration/parallel_tasks/sql.py
data_integration/ui/__init__.py
data_integration/ui/cli.py
data_integration/ui/dependency_graph.py
data_integration/ui/last_runs.py
data_integration/ui/node_page.py
data_integration/ui/run_page.py
data_integration/ui/run_time_chart.py
data_integration/ui/views.py