Metadata-Version: 2.1
Name: data-integration
Version: 2.9.0
Summary: Opinionated lightweight ETL pipeline framework
Home-page: https://github.com/mara/data-integration
Author: Mara contributors
License: MIT
Platform: UNKNOWN
Requires-Python: >=3.6
